[
	{
		"_id": "5d713995b722c3bb38c1f8d0",
		"title": "Stables",
		"description": "four bedrrooms",
		"landlord": "5c8a1d5b0190b214360dc039",
		"location": "Ruaka",
		"user": "5ed506c19df34dfab6489910"
	},
	{
		"_id": "5d713995b721c3bb38c1f5d0",
		"title": "Devworks Bootcamp",
		"description": "Devworks is a full stack JavaScript Bootcamp located in the heart of Boston that focuses on the technologies you need to get a high paying job as a web developer",
		"location": "Imara",
		"landlord": "5d7a514b5d2c12c7449be045",
		"user": "5ed506c19df34dfab6489910"
	},
	{
		"_id": "5d713a66ec8f2b88b8f830b8",
		"title": "ModernTech Bootcamp",
		"description": "ModernTech has one goal, and that is to make you a rockstar developer and/or designer with a six figure salary. We teach both development and UI/UX",
		"location": "Ndenderu",
		"landlord": "5d7a514b5d2c12c7449be046",
		"user": "5ed74f2cdd168899c69b921b"
	},
	{
		"_id": "5d725a037b292f5f8ceff787",
		"title": "Codemasters",
		"description": "Is coding your passion? Codemasters will give you the skills and the tools to become the best developer possible. We specialize in full stack web development and data science",
		"location": "Mucatha",
		"landlord": "5c8a1d5b0190b214360dc031",
		"user": "5ed74f2cdd168899c69b921b"
	},
	{
		"_id": "5d725a1b7b292f5f8ceff788",
		"title": "Devcentral Bootcamp",
		"description": "Is coding your passion? Codemasters will give you the skills and the tools to become the best developer possible. We specialize in front end and full stack web development",
		"location": "Meru",
		"landlord": "5c8a1d5b0190b214360dc032",
		"user": "5ed7512d36bc8facb8c0e25b"
	}
]
